{"bases": [{"name": "Thin", "price": 1.0, "quantity": 0}, {"name": "Thick", "price": 2.0, "quantity": 0}], "sauses": [{"name": "Tomato", "price": 1.0, "quantity": 0}, {"name": "BBQ", "price": 1.0, "quantity": 0}, {"name": "Garlic", "price": 1.0, "quantity": 0}], "toppings": [{"name": "Pepperoni", "price": 1.0, "quantity": 0}, {"name": "Ham", "price": 1.0, "quantity": 0}, {"name": "Bacon", "price": 1.0, "quantity": 0}, {"name": "Mushrooms", "price": 1.0, "quantity": 0}, {"name": "Onion", "price": 1.0, "quantity": 0}, {"name": "Black_olives", "price": 1.0, "quantity": 0}, {"name": "Tomato_slices", "price": 1.0, "quantity": 0}, {"name": "Pineapple", "price": 1.0, "quantity": 0}], "add_ingredients": [{"name": "Extra_cheese", "price": 1.0, "quantity": 0}, {"name": "Extra_meat", "price": 1.0, "quantity": 0}, {"name": "Extra_veggies", "price": 1.0, "quantity": 0}]}